[
    {
        "id":"1",
        "boxName":"Total Transaction",
        "boxNo":"5483",
        "boxIcon":"<i class='bx bx-chart-trend'></i> "       
    },
    {
        "id":"2",
        "boxName":"Credit",
        "boxNo":"300",
        "boxIcon":"<i class='bx bx-wallet-cards'></i>"
    },
    {
        "id":"3",
        "boxName":"Debit",
        "boxNo":"250",
        "boxIcon":"<i class='bx bx-credit-card'></i> "
    },
    {
        "id":"4",
        "boxName":"Invested Amount",
        "boxNo":"20",
        "boxIcon":"<i class='bx bx-signal-5'></i> "
    },
    {
        "id":"5",
        "boxName":"Weekly Limit",
        "boxNo":"30",
        "boxIcon":""
    }
]